MCF/MCF-GUI.py
MCF/MCF-parallel.py
MCF/__init__.py
MCF/helpers.py
MCF/imagetools.py
MCF/mcf.py
MCF/mcf_gui.py
MCF/mcf_parallel.py
tests/__init__.py
MiniContourFinder-1.0.19.dist-info/LICENSE
MiniContourFinder-1.0.19.dist-info/METADATA
MiniContourFinder-1.0.19.dist-info/WHEEL
MiniContourFinder-1.0.19.dist-info/entry_points.txt
MiniContourFinder-1.0.19.dist-info/top_level.txt
MiniContourFinder-1.0.19.dist-info/RECORD
